momotor/django/__init__.py
momotor/django/admin.py
momotor/django/apps.py
momotor/django/connection.py
momotor/django/defaults.py
momotor/django/fields.py
momotor/django/forms.py
momotor/django/models.py
momotor/django/tests.py
momotor/django/views.py
momotor/django/migrations/0001_initial.py
momotor/django/migrations/__init__.py
momotor/django/token_store/__init__.py
momotor/django/token_store/base.py
momotor/django/token_store/cache.py
momotor/django/token_store/dummy.py
momotor/django/token_store/memory.py
momotor/django/token_store/model.py
momotor_django-5.1.0.dist-info/METADATA
momotor_django-5.1.0.dist-info/WHEEL
momotor_django-5.1.0.dist-info/top_level.txt
momotor_django-5.1.0.dist-info/RECORD
